encrypto/__init__.py
encrypto/module.py
encryptoMe/__init__.py
encryptoMe/module.py
tests/__init__.py
tests/test_module.py
encryptoMe-0.1.dist-info/LICENSE
encryptoMe-0.1.dist-info/METADATA
encryptoMe-0.1.dist-info/WHEEL
encryptoMe-0.1.dist-info/top_level.txt
encryptoMe-0.1.dist-info/RECORD
