Metadata-Version: 2.1
Name: encryptoMe
Version: 0.1
Summary: A simple encryption library
Home-page: UNKNOWN
Author: Praneeth Raghava Vadrevu
Author-email: x23211946@student.ncirl.ie
License: MIT
Platform: UNKNOWN
Classifier: Development Status :: 3 - Alpha
Classifier: Intended Audience :: Developers
Classifier: License :: OSI Approved :: MIT License
Classifier: Programming Language :: Python :: 3
Classifier: Programming Language :: Python :: 3.7
Classifier: Programming Language :: Python :: 3.8
Classifier: Programming Language :: Python :: 3.9
License-File: LICENSE
Requires-Dist: cryptography
